{
    "Ar36": {
        "error": 0.00018022085060514148, 
        "filter_outliers_dict": {
            "filter_outliers": true, 
            "iterations": 1, 
            "std_devs": 2
        }, 
        "fit": "Parabolic", 
        "value": 0.004345144237207123
    }, 
    "Ar37": {
        "error": 0.005075981117059463, 
        "filter_outliers_dict": {
            "filter_outliers": true, 
            "iterations": 1, 
            "std_devs": 2
        }, 
        "fit": "linear", 
        "value": 0.02663719242216937
    }, 
    "Ar38": {
        "error": 0.0020653104140980765, 
        "filter_outliers_dict": {
            "filter_outliers": true, 
            "iterations": 1, 
            "std_devs": 2
        }, 
        "fit": "linear", 
        "value": -0.010269338020218755
    }, 
    "Ar39": {
        "error": 0.008997964814164426, 
        "filter_outliers_dict": {
            "filter_outliers": true, 
            "iterations": 1, 
            "std_devs": 2
        }, 
        "fit": "Parabolic", 
        "value": -0.03039668639742167
    }, 
    "Ar40": {
        "error": 0.007428882758210868, 
        "filter_outliers_dict": {
            "filter_outliers": true, 
            "iterations": 1, 
            "std_devs": 2
        }, 
        "fit": "Parabolic", 
        "value": 0.12718627150618944
    }, 
    "PM41": {
        "error": 0.06703616688304426, 
        "filter_outliers_dict": {
            "filter_outliers": false, 
            "iterations": 1, 
            "std_devs": 2
        }, 
        "fit": "linear", 
        "value": -0.1685220644242017
    }
}