{
    "Ar36": {
        "error": 0.0004663527720715875, 
        "filter_outliers_dict": {
            "filter_outliers": true, 
            "iterations": 1, 
            "std_devs": 2
        }, 
        "fit": "Linear", 
        "value": 0.040793533259089625
    }, 
    "Ar37": {
        "error": 0.009331766125113685, 
        "filter_outliers_dict": {
            "filter_outliers": true, 
            "iterations": 1, 
            "std_devs": 2
        }, 
        "fit": "linear", 
        "value": 0.8450313283996324
    }, 
    "Ar38": {
        "error": 0.005478937673305761, 
        "filter_outliers_dict": {
            "filter_outliers": true, 
            "iterations": 1, 
            "std_devs": 2
        }, 
        "fit": "linear", 
        "value": 2.621716142176303
    }, 
    "Ar39": {
        "error": 0.030515866867121943, 
        "filter_outliers_dict": {
            "filter_outliers": true, 
            "iterations": 1, 
            "std_devs": 2
        }, 
        "fit": "Linear", 
        "value": 204.94926063317644
    }, 
    "Ar40": {
        "error": 0.057235569224626144, 
        "filter_outliers_dict": {
            "filter_outliers": true, 
            "iterations": 1, 
            "std_devs": 2
        }, 
        "fit": "Linear", 
        "value": 1041.5686943987882
    }, 
    "PM41": {
        "error": 0.07110354423719219, 
        "filter_outliers_dict": {
            "filter_outliers": false, 
            "iterations": 1, 
            "std_devs": 2
        }, 
        "fit": "linear", 
        "value": -0.10620041634575163
    }
}