{
    "Ar36": {
        "error": 0.0004060161334323316, 
        "filter_outliers_dict": {
            "filter_outliers": true, 
            "iterations": 1, 
            "std_devs": 2
        }, 
        "fit": "Linear", 
        "value": 0.025153335568273268
    }, 
    "Ar37": {
        "error": 0.010703816507336213, 
        "filter_outliers_dict": {
            "filter_outliers": true, 
            "iterations": 1, 
            "std_devs": 2
        }, 
        "fit": "linear", 
        "value": 1.2232297300595567
    }, 
    "Ar38": {
        "error": 0.005661572840352226, 
        "filter_outliers_dict": {
            "filter_outliers": true, 
            "iterations": 1, 
            "std_devs": 2
        }, 
        "fit": "linear", 
        "value": 2.7557911675680757
    }, 
    "Ar39": {
        "error": 0.028189343218203676, 
        "filter_outliers_dict": {
            "filter_outliers": true, 
            "iterations": 1, 
            "std_devs": 2
        }, 
        "fit": "Linear", 
        "value": 208.00886867185503
    }, 
    "Ar40": {
        "error": 0.05967822127239566, 
        "filter_outliers_dict": {
            "filter_outliers": true, 
            "iterations": 1, 
            "std_devs": 2
        }, 
        "fit": "Linear", 
        "value": 1055.3118669873159
    }, 
    "PM41": {
        "error": 0.06377216878105164, 
        "filter_outliers_dict": {
            "filter_outliers": false, 
            "iterations": 1, 
            "std_devs": 2
        }, 
        "fit": "linear", 
        "value": -0.09970253205379553
    }
}