{
    "AX": {
        "error": 0.005352944656106123, 
        "filter_outliers_dict": {
            "filter_outliers": false, 
            "iterations": 1, 
            "std_devs": 2
        }, 
        "fit": "average_SEM", 
        "value": -0.06135874242563323
    }, 
    "H1": {
        "error": 0.003762912515742207, 
        "filter_outliers_dict": {
            "filter_outliers": false, 
            "iterations": 1, 
            "std_devs": 2
        }, 
        "fit": "average_SEM", 
        "value": -0.021887345126262656
    }, 
    "L2": {
        "error": 0.004772775840614527, 
        "filter_outliers_dict": {
            "filter_outliers": false, 
            "iterations": 1, 
            "std_devs": 2
        }, 
        "fit": "average_SEM", 
        "value": -0.021241713653400177
    }
}