{
    "Ar36": {
        "error": 0.0003260899320758189, 
        "filter_outliers_dict": {
            "filter_outliers": true, 
            "iterations": 1, 
            "std_devs": 2
        }, 
        "fit": "Parabolic", 
        "value": 0.027710665327805913
    }, 
    "Ar37": {
        "error": 0.004885794364351107, 
        "filter_outliers_dict": {
            "filter_outliers": true, 
            "iterations": 1, 
            "std_devs": 2
        }, 
        "fit": "linear", 
        "value": 0.018338272638469624
    }, 
    "Ar38": {
        "error": 0.0023071235789753107, 
        "filter_outliers_dict": {
            "filter_outliers": true, 
            "iterations": 1, 
            "std_devs": 2
        }, 
        "fit": "linear", 
        "value": 0.8351295215269463
    }, 
    "Ar39": {
        "error": 0.01394967389568985, 
        "filter_outliers_dict": {
            "filter_outliers": true, 
            "iterations": 1, 
            "std_devs": 2
        }, 
        "fit": "Parabolic", 
        "value": 65.41587741192555
    }, 
    "Ar40": {
        "error": 0.037586552977037196, 
        "filter_outliers_dict": {
            "filter_outliers": true, 
            "iterations": 1, 
            "std_devs": 2
        }, 
        "fit": "Parabolic", 
        "value": 815.6683972713329
    }, 
    "PM41": {
        "error": 0.07080020837551161, 
        "filter_outliers_dict": {
            "filter_outliers": false, 
            "iterations": 1, 
            "std_devs": 2
        }, 
        "fit": "linear", 
        "value": -0.12540377635287203
    }
}