{
    "AX": {
        "error": 0.007121689193490733, 
        "filter_outliers_dict": {
            "filter_outliers": true, 
            "iterations": 1, 
            "std_devs": 2
        }, 
        "fit": "average", 
        "value": -0.07522306143980476
    }, 
    "CDD": {
        "error": 1.3870656201763147e-05, 
        "filter_outliers_dict": {
            "filter_outliers": true, 
            "iterations": 1, 
            "std_devs": 10
        }, 
        "fit": "average", 
        "value": 8.435706672617858e-05
    }, 
    "H1": {
        "error": 0.005460631166915613, 
        "filter_outliers_dict": {
            "filter_outliers": true, 
            "iterations": 1, 
            "std_devs": 2
        }, 
        "fit": "average", 
        "value": -0.024891751013096364
    }, 
    "H2": {
        "error": 0.00873515933602325, 
        "filter_outliers_dict": {
            "filter_outliers": true, 
            "iterations": 1, 
            "std_devs": 2
        }, 
        "fit": "average", 
        "value": -0.18475990990421612
    }, 
    "L1": {
        "error": 0.002888315511338545, 
        "filter_outliers_dict": {
            "filter_outliers": true, 
            "iterations": 1, 
            "std_devs": 2
        }, 
        "fit": "average", 
        "value": -0.021984122210904074
    }, 
    "L2": {
        "error": 0.00546969880677069, 
        "filter_outliers_dict": {
            "filter_outliers": true, 
            "iterations": 1, 
            "std_devs": 2
        }, 
        "fit": "average", 
        "value": -0.0244148477002346
    }
}