{
    "AX": {
        "error": 0.007330270778586932, 
        "filter_outliers_dict": {
            "filter_outliers": true, 
            "iterations": 1, 
            "std_devs": 2
        }, 
        "fit": "average", 
        "value": -0.0719802995622317
    }, 
    "CDD": {
        "error": 1.296475511704577e-05, 
        "filter_outliers_dict": {
            "filter_outliers": true, 
            "iterations": 1, 
            "std_devs": 10
        }, 
        "fit": "average", 
        "value": 8.187597644483853e-05
    }, 
    "H1": {
        "error": 0.004320049986741757, 
        "filter_outliers_dict": {
            "filter_outliers": true, 
            "iterations": 1, 
            "std_devs": 2
        }, 
        "fit": "average", 
        "value": -0.04054926110493582
    }, 
    "H2": {
        "error": 0.008706077837229223, 
        "filter_outliers_dict": {
            "filter_outliers": true, 
            "iterations": 1, 
            "std_devs": 2
        }, 
        "fit": "average", 
        "value": -0.2131025394572537
    }, 
    "L1": {
        "error": 0.0022740117976677585, 
        "filter_outliers_dict": {
            "filter_outliers": true, 
            "iterations": 1, 
            "std_devs": 2
        }, 
        "fit": "average", 
        "value": -0.022479623141412344
    }, 
    "L2": {
        "error": 0.006997882216681223, 
        "filter_outliers_dict": {
            "filter_outliers": true, 
            "iterations": 1, 
            "std_devs": 2
        }, 
        "fit": "average", 
        "value": -0.03203496547456349
    }
}